[
  {
    "ContainingType": "GitLabAPI.Controllers.BranchController",
    "Method": "GetBranches",
    "RelativePath": "api/Branch/projects/{id}/branches",
    "HttpMethod": "GET",
    "IsController": true,
    "Order": 0,
    "Parameters": [
      {
        "Name": "id",
        "Type": "System.Int32",
        "IsRequired": true
      }
    ],
    "ReturnTypes": []
  },
  {
    "ContainingType": "GitLabAPI.Controllers.BranchController",
    "Method": "CreateBranch",
    "RelativePath": "api/Branch/projects/{id}/createbranch",
    "HttpMethod": "POST",
    "IsController": true,
    "Order": 0,
    "Parameters": [
      {
        "Name": "id",
        "Type": "System.Int32",
        "IsRequired": true
      },
      {
        "Name": "request",
        "Type": "EntityLayer.BranchAndCommit",
        "IsRequired": true
      }
    ],
    "ReturnTypes": []
  },
  {
    "ContainingType": "GitLabAPI_2.Controllers.CommitController",
    "Method": "Index",
    "RelativePath": "api/Commit",
    "HttpMethod": "",
    "IsController": true,
    "Order": 0,
    "Parameters": [],
    "ReturnTypes": []
  },
  {
    "ContainingType": "GitLabAPI_2.Controllers.CommitController",
    "Method": "GetCommites",
    "RelativePath": "api/Commit/project/{projectId}/commites",
    "HttpMethod": "GET",
    "IsController": true,
    "Order": 0,
    "Parameters": [
      {
        "Name": "projectId",
        "Type": "System.Int32",
        "IsRequired": true
      }
    ],
    "ReturnTypes": []
  },
  {
    "ContainingType": "GitLabAPI_2.Controllers.CommitController",
    "Method": "CreateCommites",
    "RelativePath": "api/Commit/project/{projectId}/createcommit",
    "HttpMethod": "POST",
    "IsController": true,
    "Order": 0,
    "Parameters": [
      {
        "Name": "projectId",
        "Type": "System.Int32",
        "IsRequired": true
      },
      {
        "Name": "request",
        "Type": "GitLabAPI_2.Controllers.CreateCommitRequest",
        "IsRequired": true
      }
    ],
    "ReturnTypes": []
  },
  {
    "ContainingType": "GitLabAPI.Controllers.GroupController",
    "Method": "GetGroups",
    "RelativePath": "api/Group/groups",
    "HttpMethod": "GET",
    "IsController": true,
    "Order": 0,
    "Parameters": [],
    "ReturnTypes": []
  },
  {
    "ContainingType": "GitLabAPI.Controllers.GroupController",
    "Method": "GetProjectsByGroupId",
    "RelativePath": "api/Group/groups/{groupId}/projects",
    "HttpMethod": "GET",
    "IsController": true,
    "Order": 0,
    "Parameters": [
      {
        "Name": "groupId",
        "Type": "System.Int32",
        "IsRequired": true
      }
    ],
    "ReturnTypes": []
  },
  {
    "ContainingType": "GitLabAPI.Controllers.GroupController",
    "Method": "GetNuGetPackagesByGroupId",
    "RelativePath": "api/Group/groups/{groupId}/projects/packages",
    "HttpMethod": "GET",
    "IsController": true,
    "Order": 0,
    "Parameters": [
      {
        "Name": "groupId",
        "Type": "System.Int32",
        "IsRequired": true
      },
      {
        "Name": "searchTerm",
        "Type": "System.String",
        "IsRequired": false
      }
    ],
    "ReturnTypes": []
  },
  {
    "ContainingType": "GitLabAPI.Controllers.GroupController",
    "Method": "UpdatePackageVersion",
    "RelativePath": "api/Group/update-package-version",
    "HttpMethod": "PUT",
    "IsController": true,
    "Order": 0,
    "Parameters": [
      {
        "Name": "projectName",
        "Type": "System.String",
        "IsRequired": false
      },
      {
        "Name": "packageId",
        "Type": "System.String",
        "IsRequired": false
      },
      {
        "Name": "version",
        "Type": "System.String",
        "IsRequired": false
      }
    ],
    "ReturnTypes": []
  },
  {
    "ContainingType": "GitLabAPI_2.Controllers.MergeController",
    "Method": "GetMerges",
    "RelativePath": "api/Merge/{id}/merges",
    "HttpMethod": "GET",
    "IsController": true,
    "Order": 0,
    "Parameters": [
      {
        "Name": "id",
        "Type": "System.Int32",
        "IsRequired": true
      }
    ],
    "ReturnTypes": []
  }
]